odoo/addons/project_task_stage_change_restriction/README.rst
odoo/addons/project_task_stage_change_restriction/__init__.py
odoo/addons/project_task_stage_change_restriction/__manifest__.py
odoo/addons/project_task_stage_change_restriction/data/demo_project_task_stage.xml
odoo/addons/project_task_stage_change_restriction/i18n/.empty
odoo/addons/project_task_stage_change_restriction/i18n/it.po
odoo/addons/project_task_stage_change_restriction/i18n/project_task_stage_change_restriction.pot
odoo/addons/project_task_stage_change_restriction/models/__init__.py
odoo/addons/project_task_stage_change_restriction/models/project_task.py
odoo/addons/project_task_stage_change_restriction/models/project_task_type.py
odoo/addons/project_task_stage_change_restriction/readme/CONFIGURE.md
odoo/addons/project_task_stage_change_restriction/readme/CONTEXT.md
odoo/addons/project_task_stage_change_restriction/readme/CONTRIBUTORS.md
odoo/addons/project_task_stage_change_restriction/readme/DESCRIPTION.md
odoo/addons/project_task_stage_change_restriction/readme/USAGE.md
odoo/addons/project_task_stage_change_restriction/readme/newsfragments/.gitkeep
odoo/addons/project_task_stage_change_restriction/static/description/icon.png
odoo/addons/project_task_stage_change_restriction/static/description/index.html
odoo/addons/project_task_stage_change_restriction/tests/__init__.py
odoo/addons/project_task_stage_change_restriction/tests/test_stage_change_restriction.py
odoo/addons/project_task_stage_change_restriction/views/project_task_stage_views.xml
odoo_addon_project_task_stage_change_restriction-18.0.1.0.0.2.dist-info/METADATA
odoo_addon_project_task_stage_change_restriction-18.0.1.0.0.2.dist-info/WHEEL
odoo_addon_project_task_stage_change_restriction-18.0.1.0.0.2.dist-info/top_level.txt
odoo_addon_project_task_stage_change_restriction-18.0.1.0.0.2.dist-info/RECORD
