Metadata-Version: 2.1
Name: odoo-addon-project_task_stage_change_restriction
Version: 18.0.1.0.0.2
Requires-Python: >=3.10
Requires-Dist: odoo==18.0.*
Summary: Restrict project task stage
Home-page: https://github.com/OCA/project
License: AGPL-3
Author: Odoo Community Association (OCA), Cetmix
Author-email: support@odoo-community.org
Classifier: Programming Language :: Python
Classifier: Framework :: Odoo
Classifier: Framework :: Odoo :: 18.0
Classifier: License :: OSI Approved :: GNU Affero General Public License v3
